.DS_Store
TimelineNetworkUtility/__init__.py
TimelineNetworkUtility/__pycache__/__init__.cpython-35.pyc
TimelineNetworkUtility_zzenlightenzz-0.1.6.dist-info/LICENSE
TimelineNetworkUtility_zzenlightenzz-0.1.6.dist-info/METADATA
TimelineNetworkUtility_zzenlightenzz-0.1.6.dist-info/WHEEL
TimelineNetworkUtility_zzenlightenzz-0.1.6.dist-info/top_level.txt
TimelineNetworkUtility_zzenlightenzz-0.1.6.dist-info/RECORD
