Metadata-Version: 2.1
Name: TimelineNetworkUtility-zzenlightenzz
Version: 0.1.6
Summary: This is a small library that composing of Timeline and Network utility function.
Home-page: UNKNOWN
Author: Worawut Boonpeang
Author-email: 
License: UNKNOWN
Platform: UNKNOWN
Classifier: Programming Language :: Python :: 3
Classifier: License :: OSI Approved :: MIT License
Classifier: Operating System :: OS Independent
Requires-Python: >=3.6
